<?xml version="1.0" encoding="utf-8" ?>
<dwsync>
<file name="boligapplikation-myhome.jpg" server="ftp.designbymelsted.dk" local="131888524178521405" remote="131897899800000000" Dst="1" />
<file name="colorscheme.jpg" server="ftp.designbymelsted.dk" local="131897612996130512" remote="131897899800000000" Dst="1" />
<file name="howtoletterform.jpg" server="ftp.designbymelsted.dk" local="131897606105897593" remote="131897899800000000" Dst="1" />
<file name="howtologo.jpg" server="ftp.designbymelsted.dk" local="131897604083166653" remote="131897899800000000" Dst="1" />
<file name="me.try04.png" server="ftp.designbymelsted.dk" local="131830295196504777" remote="131897899800000000" Dst="1" />
<file name="ommig.jpg" server="ftp.designbymelsted.dk" local="131896864200811294" remote="131897899800000000" Dst="1" />
<file name="ommig1.jpg" server="ftp.designbymelsted.dk" local="131896930131017990" remote="131897899800000000" Dst="1" />
<file name="portfolio.jpg" server="ftp.designbymelsted.dk" local="131897857276938953" remote="131897899800000000" Dst="1" />
<file name="screenshot.jpg" server="ftp.designbymelsted.dk" local="131897851509363721" remote="131897899800000000" Dst="1" />
</dwsync>